{"title":"오디오클립 ─ 놓치면 후회할 영화","url":"https://audioclip.naver.com/channels/2875","favicon":"https://audioclip.naver.com/channels/favicon.ico","elements":[{"title":"[오마주] 현장에서 감독으로 불렸던 '이정은'?, 필름에 새긴 여성 영화인의 꿈 '오마주'(w.'신수원' 감독)","contents":"<span class=\"blind\">재생시간</span>48분","link":"https://audioclip.naver.com/channels/2875/clips/162","retrieved":1653535576651,"image":"https://audio-phinf.pstatic.net/20220526_242/1653531892431aJGPG_JPEG/124a.jpg?type=f150_150"},{"title":"[업] 가정의 달, 온 가족이 모여 꿈을 그려볼 수 있는 명작 애니메이션","contents":"<span class=\"blind\">재생시간</span>33분","link":"https://audioclip.naver.com/channels/2875/clips/161","retrieved":1653360621795,"image":"https://audio-phinf.pstatic.net/20220524_189/165332481639689mkC_JPEG/2a.jpg?type=f150_150"},{"title":"[범죄도시2] 1편보다 더 재밌다? 진실의 방으로!(잠시 쉬었다 가는 '영화잡썰')","contents":"<span class=\"blind\">재생시간</span>39분","link":"https://audioclip.naver.com/channels/2875/clips/160","retrieved":1653360621801,"image":"https://audio-phinf.pstatic.net/20220520_165/1653058029993SlAS7_JPEG/122a.jpg?type=f150_150"},{"title":"[영화 추천] '닥터 스트레인지', 베네딕트 컴버배치가 출연한 실화 영화","contents":"<span class=\"blind\">재생시간</span>15분","link":"https://audioclip.naver.com/channels/2875/clips/159","retrieved":1653360621808,"image":"https://audio-phinf.pstatic.net/20220518_165/1652855138595fbLlh_JPEG/4a.jpg?type=f150_150"},{"title":"[영화 추천] 여름의 청량함을 잔뜩 느낄 수 있는 음악 영화(코다, 싱 스트리트, 맘마미아)","contents":"<span class=\"blind\">재생시간</span>22분","link":"https://audioclip.naver.com/channels/2875/clips/158","retrieved":1653360621809},{"title":"[파친코] '파친코'라는 제목에 담긴 의미","contents":"<span class=\"blind\">재생시간</span>49분","link":"https://audioclip.naver.com/channels/2875/clips/157","retrieved":1652113851603},{"title":"[영화 추천] 이게 벌써? '디즈니플러스'에서 볼 수 있는 핫한 신작(킹스맨, 웨스트사이드 스토리, 나이트메어 앨리)","contents":"<span class=\"blind\">재생시간</span>23분","link":"https://audioclip.naver.com/channels/2875/clips/156","retrieved":1651764038703},{"title":"[기묘한 이야기] 이번 달 '넷플릭스'를 구독해야만 하는 이유(기묘한 이야기, 클라르크, 안나라수마나라)","contents":"<span class=\"blind\">재생시간</span>24분","link":"https://audioclip.naver.com/channels/2875/clips/155","retrieved":1651526110403},{"title":"[노트북] 우리는 이런 사랑을 할 수 있을까? '영화' 같은 로맨스의 교과서!","contents":"<span class=\"blind\">재생시간</span>35분","link":"https://audioclip.naver.com/channels/2875/clips/154","retrieved":1651220796869},{"title":"[영화 추천] 봄의 감성을 닮은 다양한 장르의 영화들","contents":"<span class=\"blind\">재생시간</span>13분","link":"https://audioclip.naver.com/channels/2875/clips/153","retrieved":1651220796870}]}