{"title":"오디오클립 ─ 씨네타운","url":"https://audioclip.naver.com/channels/1417","favicon":"https://audioclip.naver.com/channels/favicon.ico","elements":[{"title":"(수) - 위클리매거진 (박혜은 편집장) - 2022.7.13","contents":"<span class=\"blind\">재생시간</span>27분","link":"https://audioclip.naver.com/channels/1417/clips/2233","retrieved":1657696689672,"image":"https://audio-phinf.pstatic.net/20220713_73/1657696432491ngQnm_JPEG/0fc9b3ee3da22e3d46bccfd83d410a426f83408ff4806a9b6b9f1691ecf50aa1d0670aca7bc70412.jpeg?type=f150_150"},{"title":"(화) - 씨네체크인 (럭키) - 2022.7.12","contents":"<span class=\"blind\">재생시간</span>30분","link":"https://audioclip.naver.com/channels/1417/clips/2232","retrieved":1657610301723,"image":"https://audio-phinf.pstatic.net/20220712_215/1657608228058lyhGt_JPEG/0fc9b3ee3da22e3d46bccfd83d410a426f83408ff4806a9b6b9f1691ecf50aa1d0670aca7bc70412.jpeg?type=f150_150"},{"title":"(월) - 씨네맛 천국 (파란달) - 2022.7.11","contents":"<span class=\"blind\">재생시간</span>25분","link":"https://audioclip.naver.com/channels/1417/clips/2231","retrieved":1657523914663,"image":"https://audio-phinf.pstatic.net/20220711_222/1657521827488zaGWF_JPEG/0fc9b3ee3da22e3d46bccfd83d410a426f83408ff4806a9b6b9f1691ecf50aa1d0670aca7bc70412.jpeg?type=f150_150"},{"title":"(일) - 한드의 품격 - 2022.7.10","contents":"<span class=\"blind\">재생시간</span>12분","link":"https://audioclip.naver.com/channels/1417/clips/2230","retrieved":1657462598209,"image":"https://audio-phinf.pstatic.net/20220710_120/1657462452089monkr_JPEG/0fc9b3ee3da22e3d46bccfd83d410a426f83408ff4806a9b6b9f1691ecf50aa1d0670aca7bc70412.jpeg?type=f150_150"},{"title":"(토) - 좋아하면 들리는 퀴즈 - 2022.7.9","contents":"<span class=\"blind\">재생시간</span>14분","link":"https://audioclip.naver.com/channels/1417/clips/2229","retrieved":1657376182499},{"title":"(금) - 위클리매거진 (박혜은 편집장) - 2022.7.8","contents":"<span class=\"blind\">재생시간</span>23분","link":"https://audioclip.naver.com/channels/1417/clips/2228","retrieved":1657264683682},{"title":"(목) - 씨네초대석 (장혁) - 2022.7.7","contents":"<span class=\"blind\">재생시간</span>35분","link":"https://audioclip.naver.com/channels/1417/clips/2227","retrieved":1657178347709},{"title":"(수) - 퀴즈쇼 - 식스센스 - 2022.7.6","contents":"<span class=\"blind\">재생시간</span>19분","link":"https://audioclip.naver.com/channels/1417/clips/2226","retrieved":1657091914561},{"title":"(화) - 초희's 초이스 (김초희 감독) - 2022.7.5","contents":"<span class=\"blind\">재생시간</span>25분","link":"https://audioclip.naver.com/channels/1417/clips/2225","retrieved":1657002237998},{"title":"(월) - 씨네초대석 (박해일, 변요한) - 2022.7.4","contents":"<span class=\"blind\">재생시간</span>42분","link":"https://audioclip.naver.com/channels/1417/clips/2224","retrieved":1656919218360}]}